gocharts/ChartExporter.py
gocharts/Display.py
gocharts/Facet.py
gocharts/Generator.py
gocharts/GoChartClass.py
gocharts/Theme.py
gocharts/__init__.py
gocharts/template.py
gocharts/utils.py
gocharts-0.1.0.dist-info/licenses/LICENSE
gocharts-0.1.0.dist-info/METADATA
gocharts-0.1.0.dist-info/WHEEL
gocharts-0.1.0.dist-info/top_level.txt
gocharts-0.1.0.dist-info/RECORD
