Metadata-Version: 2.4
Name: gocharts
Version: 0.1.0
Summary: A Python charting library with support for pandas, polars, and numpy.
Author-email: Edvinas Drevinskas <e.drevinskas@gmail.com>
License-Expression: GPL-3.0-or-later
Requires-Python: >=3.10
License-File: LICENSE
Requires-Dist: polars>=0.17.0
Requires-Dist: pandas>=1.3.0
Requires-Dist: numpy>=1.21.0
Provides-Extra: dev
Requires-Dist: pytest; extra == "dev"
Requires-Dist: black; extra == "dev"
Requires-Dist: flake8; extra == "dev"
Dynamic: license-file
